psychos/__init__.py
psychos/__version__.py
psychos/types.py
psychos/core/__init__.py
psychos/core/interact.py
psychos/core/keys.py
psychos/core/time.py
psychos/gui/__init__.py
psychos/gui/dialog.py
psychos/sound/__init__.py
psychos/sound/sound.py
psychos/triggers/__init__.py
psychos/triggers/ports.py
psychos/triggers/triggers.py
psychos/utils/__init__.py
psychos/utils/colors.py
psychos/utils/decorators.py
psychos/utils/lazy.py
psychos/utils/screens.py
psychos/visual/__init__.py
psychos/visual/bordered_rectangle.py
psychos/visual/circle.py
psychos/visual/gabor.py
psychos/visual/image.py
psychos/visual/raw_image.py
psychos/visual/rectangle.py
psychos/visual/slider.py
psychos/visual/synthetic.py
psychos/visual/text.py
psychos/visual/units.py
psychos/visual/window.py
psychos-0.0.6.dist-info/licenses/LICENSE
psychos-0.0.6.dist-info/METADATA
psychos-0.0.6.dist-info/WHEEL
psychos-0.0.6.dist-info/top_level.txt
psychos-0.0.6.dist-info/RECORD
