Metadata-Version: 2.4
Name: psychos
Version: 0.0.6
Summary: Package for creating experiments for behavioural research.
Author-email: Dynamics of Memory Formation Group <llfuentemilla@ub.edu>
Maintainer-email: Pablo Marcos-Manchón <pmarcos@ub.edu>
License: MIT
Project-URL: repository, https://github.com/memory-formation/psychos
Keywords: psychology,behavioural,experiments,neuroscience,research,python,pyglet
Classifier: Development Status :: 4 - Beta
Classifier: Intended Audience :: Developers
Classifier: Intended Audience :: Science/Research
Classifier: License :: OSI Approved :: MIT License
Classifier: Natural Language :: English
Classifier: Operating System :: MacOS :: MacOS X
Classifier: Operating System :: Microsoft :: Windows
Classifier: Operating System :: POSIX :: Linux
Classifier: Programming Language :: Python :: 3.8
Classifier: Programming Language :: Python :: 3.9
Classifier: Programming Language :: Python :: 3.10
Classifier: Programming Language :: Python :: 3.11
Classifier: Programming Language :: Python :: 3.12
Classifier: Topic :: Scientific/Engineering
Classifier: Topic :: Software Development :: Libraries :: Python Modules
Requires-Python: >=3.8
License-File: LICENSE
Requires-Dist: pyglet>=2.0.0
Provides-Extra: docs
Requires-Dist: sphinx==8.0.2; extra == "docs"
Requires-Dist: pydata-sphinx-theme; extra == "docs"
Provides-Extra: extra
Requires-Dist: numpy>=1.20; extra == "extra"
Requires-Dist: pyparallel; extra == "extra"
Requires-Dist: pyserial; extra == "extra"
Provides-Extra: test
Requires-Dist: pytest; extra == "test"
Dynamic: license-file
